{
  "discount" : {
    "id": "ID",
    "code": "Код скидки",
    "is_used": "Использован",
    "date_used": "Дата использования",
    "date_created": "Дата создания",
    "time_used" : "Время использования",
    "active": "Активный код",
    "discount_type": "Тип скидки",
    "title": "Название",
    "descr": "Описание",
    "amount" : "Значение",
    "is_percents": "Процентная скидка",
    "ticket_amount": "Количество билетов",
    "is_active": "Активная скидка",
    "date_from": "С (дата)",
    "date_to" : "До (дата)",
    "with_discount": "Отображать цену с учетом скидки",
    "round": "Округлять",
    "multi_discount": "Мультискидка",
    "multi_ticket" : "Скидка на каждый N билет",
    "eticket_enabled": "Eticket включен",
    "delivery_enabled": "Доставка включена",
    "bind_to_every_new_event": "Связывается с каждым новым событием"
  },
  "order" :
  {
    "lastname" : "Фамилия",
    "firstname" : "Имя",
    "city_name" : "город",
    "age" : "Возраст",
    "email" : "E-mail",
    "mobile" : "Номер телефона",
    "price_total" : "Общая цена",
    "price_subtotal" : "Цена",
    "price_fee" : "Уплаченая стоимость",
    "tax_price" : "Такса",
    "price_currency" : "Валюта",
    "ip_address" : "IP адресс",
    "date_created" : "Дата создания",
    "date_confirmed" : "Дата подтверждения",
    "payment_type" : "Способ оплаты",
    "payment_subtype" : "",
    "secret_code" : "Секретный код",
    "billing_price" : "Билинговая цена",
    "billing_fee" : "Оплата по биллингу",
    "billing_currency" : "Биллинговая валюта",
    "discount" : "Скидка",
    "is_test" : "Тестовый заказ",
    "is_deposit" : "Есть депозит",
    "cancelled_reason" : "Причина отмены",
    "date_cancelled" : "Дата отмены",
    "is_deposit_payment" : "",
    "is_free" : "Бесплатный",
    "is_external" : "Внешний",
    "karabas_expired" : "",
    "sub_domain" : "Поддомен",
    "is_concert" : "Концерт",
    "is_send" : "Продан",
    "delivery_price" : "Цена доставки",
    "delivery_type" : "Тип доставки",
    "is_register" : "Бронь",
    "delivery_expired" : "Окончание доставки",
    "reserv_cancelling" : "Дата окончания брони",
    "max_reservation_date" : "Максимальная дата брони"
  }

}